pydemolib/__init__.py
pydemolib/module1.py
pydemolib-0.1.0.dist-info/METADATA
pydemolib-0.1.0.dist-info/WHEEL
pydemolib-0.1.0.dist-info/top_level.txt
pydemolib-0.1.0.dist-info/RECORD
