Metadata-Version: 2.1
Name: pydemolib
Version: 0.1.0
Summary: A simple example library
Home-page: https://github.com/dineshsuthar03/pydemolib
Author: Dinesh
Author-email: dineshsutharinfo@gmail.com
Classifier: Programming Language :: Python :: 3
Classifier: License :: OSI Approved :: MIT License
Classifier: Operating System :: OS Independent
Requires-Python: >=3.6
